<?xml version="1.0" encoding="utf-8"?>
<class id="f4515911-7028-4591-817f-0b0bc6c63049" type="Folder" typeId="4d95d53a-8855-4f35-aa82-e312643f5c5f">
  <name>src</name>
  <display>src</display>
  <isAbstract>false</isAbstract>
  <order>0</order>
  <genericTypes />
  <isMapped>false</isMapped>
  <parentFolderId>6a88e337-e454-4c78-958d-698b9030bd40</parentFolderId>
  <stereotypes />
  <childElements>
    <childElement id="20960ac2-13b5-453d-8eee-b8107a717d3b" type="Folder" typeId="4d95d53a-8855-4f35-aa82-e312643f5c5f">
      <name>main</name>
      <display>main</display>
      <isAbstract>false</isAbstract>
      <order>0</order>
      <genericTypes />
      <isMapped>false</isMapped>
      <parentFolderId>f4515911-7028-4591-817f-0b0bc6c63049</parentFolderId>
      <stereotypes />
      <childElements>
        <childElement id="d6727200-81fe-4537-8e8e-6fab10d7b129" type="Folder" typeId="4d95d53a-8855-4f35-aa82-e312643f5c5f">
          <name>java</name>
          <display>java</display>
          <isAbstract>false</isAbstract>
          <order>0</order>
          <genericTypes />
          <isMapped>false</isMapped>
          <parentFolderId>20960ac2-13b5-453d-8eee-b8107a717d3b</parentFolderId>
          <stereotypes />
          <childElements>
            <childElement id="8c4b8554-9b3e-4142-900b-f9be9995658a" type="Folder" typeId="4d95d53a-8855-4f35-aa82-e312643f5c5f">
              <name>com</name>
              <display>com</display>
              <isAbstract>false</isAbstract>
              <order>0</order>
              <genericTypes />
              <isMapped>false</isMapped>
              <parentFolderId>d6727200-81fe-4537-8e8e-6fab10d7b129</parentFolderId>
              <stereotypes />
              <childElements>
                <childElement id="067550a3-48cd-496d-a9b8-e64b2f17bc95" type="Folder" typeId="4d95d53a-8855-4f35-aa82-e312643f5c5f">
                  <name>Samples</name>
                  <display>Samples</display>
                  <isAbstract>false</isAbstract>
                  <order>0</order>
                  <genericTypes />
                  <isMapped>false</isMapped>
                  <parentFolderId>8c4b8554-9b3e-4142-900b-f9be9995658a</parentFolderId>
                  <stereotypes />
                  <childElements>
                    <childElement id="5282e06c-e5d2-4270-96ea-16deaa94e104" type="Folder" typeId="4d95d53a-8855-4f35-aa82-e312643f5c5f">
                      <name>SpringBoot.App</name>
                      <display>SpringBoot.App</display>
                      <isAbstract>false</isAbstract>
                      <order>0</order>
                      <genericTypes />
                      <isMapped>false</isMapped>
                      <parentFolderId>067550a3-48cd-496d-a9b8-e64b2f17bc95</parentFolderId>
                      <stereotypes />
                      <childElements>
                        <childElement id="e94fa53a-8941-4ca0-b018-52d9886d93ce" type="Folder" typeId="4d95d53a-8855-4f35-aa82-e312643f5c5f">
                          <name>application</name>
                          <display>application</display>
                          <isAbstract>false</isAbstract>
                          <order>0</order>
                          <genericTypes />
                          <isMapped>false</isMapped>
                          <parentFolderId>5282e06c-e5d2-4270-96ea-16deaa94e104</parentFolderId>
                          <stereotypes />
                          <childElements>
                            <childElement id="59aca62f-69ea-4b36-a784-520b94e293e1" type="Role" typeId="8663c9f9-2852-45e7-aaa1-0883a2e6f1da">
                              <name>Application</name>
                              <display>Application</display>
                              <isAbstract>false</isAbstract>
                              <order>0</order>
                              <genericTypes />
                              <isMapped>false</isMapped>
                              <parentFolderId>e94fa53a-8941-4ca0-b018-52d9886d93ce</parentFolderId>
                              <stereotypes />
                              <childElements />
                            </childElement>
                          </childElements>
                        </childElement>
                        <childElement id="e28bdd77-8e81-4926-9641-b010122e9ba9" type="Folder" typeId="4d95d53a-8855-4f35-aa82-e312643f5c5f">
                          <name>domain</name>
                          <display>domain</display>
                          <isAbstract>false</isAbstract>
                          <order>0</order>
                          <genericTypes />
                          <isMapped>false</isMapped>
                          <parentFolderId>5282e06c-e5d2-4270-96ea-16deaa94e104</parentFolderId>
                          <stereotypes />
                          <childElements>
                            <childElement id="d9a0506e-8cb6-45d7-8d2a-9bd6417af077" type="Role" typeId="8663c9f9-2852-45e7-aaa1-0883a2e6f1da">
                              <name>Domain</name>
                              <display>Domain</display>
                              <isAbstract>false</isAbstract>
                              <order>0</order>
                              <genericTypes />
                              <isMapped>false</isMapped>
                              <parentFolderId>e28bdd77-8e81-4926-9641-b010122e9ba9</parentFolderId>
                              <stereotypes />
                              <childElements />
                            </childElement>
                          </childElements>
                        </childElement>
                        <childElement id="9e0aa13c-9cd5-4672-9c72-a2aac804ad83" type="Role" typeId="8663c9f9-2852-45e7-aaa1-0883a2e6f1da">
                          <name>Startup</name>
                          <display>Startup</display>
                          <isAbstract>false</isAbstract>
                          <order>0</order>
                          <genericTypes />
                          <isMapped>false</isMapped>
                          <parentFolderId>5282e06c-e5d2-4270-96ea-16deaa94e104</parentFolderId>
                          <stereotypes />
                          <childElements />
                        </childElement>
                        <childElement id="5e39fa2b-1d33-4d99-a6dc-7242c53c0e63" type="Template Output" typeId="09de2192-2507-41a2-8044-286c7ecadec2">
                          <name>Intent.Java.SpringBoot.Application</name>
                          <display>Intent.Java.SpringBoot.Application</display>
                          <externalReference>Intent.Java.SpringBoot</externalReference>
                          <isAbstract>false</isAbstract>
                          <order>0</order>
                          <genericTypes />
                          <isMapped>false</isMapped>
                          <parentFolderId>5282e06c-e5d2-4270-96ea-16deaa94e104</parentFolderId>
                          <stereotypes />
                          <childElements />
                        </childElement>
                      </childElements>
                    </childElement>
                  </childElements>
                </childElement>
              </childElements>
            </childElement>
          </childElements>
        </childElement>
      </childElements>
    </childElement>
  </childElements>
</class>